LICENSE
README.md
setup.py
pyseistr/__init__.py
pyseistr/bp.py
pyseistr/das.py
pyseistr/dip2d.py
pyseistr/dip3d.py
pyseistr/divne.py
pyseistr/fk.py
pyseistr/mf.py
pyseistr/operators.py
pyseistr/plot.py
pyseistr/pwsmooth.py
pyseistr/pwspray2d.py
pyseistr/pwspray3d.py
pyseistr/rgt.py
pyseistr/ricker.py
pyseistr/sint.py
pyseistr/smooth.py
pyseistr/soint2d.py
pyseistr/soint3d.py
pyseistr/solvers.py
pyseistr/somean2d.py
pyseistr/somean3d.py
pyseistr/somf2d.py
pyseistr/somf3d.py
pyseistr/synthetics.py
pyseistr.egg-info/PKG-INFO
pyseistr.egg-info/SOURCES.txt
pyseistr.egg-info/dependency_links.txt
pyseistr.egg-info/not-zip-safe
pyseistr.egg-info/requires.txt
pyseistr.egg-info/top_level.txt
pyseistr/src/bp_cfuns.c
pyseistr/src/coh_cfuns.c
pyseistr/src/dip_cfuns.c
pyseistr/src/paint_cfuns.c
pyseistr/src/sof3d_cfuns.c
pyseistr/src/sof_cfuns.c
pyseistr/src/soint2d_cfuns.c
pyseistr/src/soint3d_cfuns.c